Metadata-Version: 2.1
Name: odoo-addon-intrastat_product
Version: 18.0.1.1.2
Requires-Python: >=3.10
Requires-Dist: odoo-addon-intrastat_base==18.0.*
Requires-Dist: odoo-addon-product_harmonized_system==18.0.*
Requires-Dist: odoo-addon-report_xlsx_helper==18.0.*
Requires-Dist: odoo==18.0.*
Summary: Base module for Intrastat Product
Home-page: https://github.com/OCA/intrastat-extrastat
License: AGPL-3
Author: ACSONE SA/NV, brain-tec AG, Akretion, Noviat, Odoo Community Association (OCA)
Author-email: support@odoo-community.org
Classifier: Programming Language :: Python
Classifier: Framework :: Odoo
Classifier: Framework :: Odoo :: 18.0
Classifier: License :: OSI Approved :: GNU Affero General Public License v3
